{
  "@context": "https://linked.art/ns/v1/linked-art.json",
  "id": "https://clevelandart.org/art/1921.321",
  "type": "HumanMadeObject",
  "_label": "Woman Performing the Tea Ceremony",
  "identified_by": [
    {
      "id": "https://clevelandart.org/art/object/1921.321/title",
      "type": "Name",
      "_label": "Primary Title for the Object",
      "content": "Woman Performing the Tea Ceremony",
      "classified_as": [
        {
          "id": "http://vocab.getty.edu/aat/300404670",
          "type": "Type",
          "_label": "preferred terms"
        }
      ]
    }
  ],
  "referred_to_by": [
    {
      "id": "https://clevelandart.org/art/object/1921.321/credit-line",
      "type": "LinguisticObject",
      "_label": "Credit Line for the Object",
      "content": "Kikukawa Eizan (Japanese, 1787-1867), artist",
      "classified_as": [
        {
          "id": "http://vocab.getty.edu/aat/300026687",
          "type": "Type",
          "_label": "acknowledgments"
        },
        {
          "id": "http://vocab.getty.edu/aat/300418049",
          "type": "Type",
          "_label": "brief texts"
        }
      ]
    },
    {
      "id": "https://clevelandart.org/art/object/1921.321/provenance-statement",
      "type": "LinguisticObject",
      "_label": "Provenance Statement about the Object",
      "content": "Carl Schraubstadter Collection (sale: American Art Association, February 11, 1921, lot 595); (Yamanaka & Co.)",
      "classified_as": [
        {
          "id": "http://vocab.getty.edu/aat/300055863",
          "type": "Type",
          "_label": "provenance (history of ownership)"
        },
        {
          "id": "http://vocab.getty.edu/aat/300418049",
          "type": "Type",
          "_label": "brief texts"
        }
      ]
    }
  ],
  "produced_by": [
    {
      "id": "https://clevelandart.org/art/object/1921.321/production",
      "type": "Production",
      "_label": "Production of the Object"
    },
    {
      "carried_out_by": [
        {
          "id": "https://clevelandart.org/art/actor/1921.321",
          "type": "Actor",
          "_label": ""
        }
      ]
    },
    {
      "timespan": {
        "id": "https://clevelandart.org/art/1921.321/production/timespan",
        "type": "TimeSpan",
        "_label": "c. 1820",
        "begin_of_the_begin": "1815",
        "end_of_the_end": "1825"
      }
    }
  ]
}