{
  "@context": "https://linked.art/ns/v1/linked-art.json",
  "id": "https://clevelandart.org/art/1922.126",
  "type": "HumanMadeObject",
  "_label": "Eight Nude Children at a Well",
  "identified_by": [
    {
      "id": "https://clevelandart.org/art/object/1922.126/title",
      "type": "Name",
      "_label": "Primary Title for the Object",
      "content": "Eight Nude Children at a Well",
      "classified_as": [
        {
          "id": "http://vocab.getty.edu/aat/300404670",
          "type": "Type",
          "_label": "preferred terms"
        }
      ]
    }
  ],
  "referred_to_by": [
    {
      "id": "https://clevelandart.org/art/object/1922.126/credit-line",
      "type": "LinguisticObject",
      "_label": "Credit Line for the Object",
      "content": "Heinrich Aldegrever (German, 1502-1555/61), artist",
      "classified_as": [
        {
          "id": "http://vocab.getty.edu/aat/300026687",
          "type": "Type",
          "_label": "acknowledgments"
        },
        {
          "id": "http://vocab.getty.edu/aat/300418049",
          "type": "Type",
          "_label": "brief texts"
        }
      ]
    }
  ],
  "produced_by": [
    {
      "id": "https://clevelandart.org/art/object/1922.126/production",
      "type": "Production",
      "_label": "Production of the Object"
    },
    {
      "carried_out_by": [
        {
          "id": "https://clevelandart.org/art/actor/1922.126",
          "type": "Actor",
          "_label": ""
        }
      ]
    },
    {
      "timespan": {
        "id": "https://clevelandart.org/art/1922.126/production/timespan",
        "type": "TimeSpan",
        "_label": "1539",
        "begin_of_the_begin": "1539",
        "end_of_the_end": "1539"
      }
    }
  ]
}