{
  "@context": "https://linked.art/ns/v1/linked-art.json",
  "id": "https://clevelandart.org/art/1924.655",
  "type": "HumanMadeObject",
  "_label": "The Two Gossips",
  "identified_by": [
    {
      "id": "https://clevelandart.org/art/object/1924.655/title",
      "type": "Name",
      "_label": "Primary Title for the Object",
      "content": "The Two Gossips",
      "classified_as": [
        {
          "id": "http://vocab.getty.edu/aat/300404670",
          "type": "Type",
          "_label": "preferred terms"
        }
      ]
    }
  ],
  "referred_to_by": [
    {
      "id": "https://clevelandart.org/art/object/1924.655/credit-line",
      "type": "LinguisticObject",
      "_label": "Credit Line for the Object",
      "content": "Adriaen van Ostade (Dutch, 1610-1684), artist",
      "classified_as": [
        {
          "id": "http://vocab.getty.edu/aat/300026687",
          "type": "Type",
          "_label": "acknowledgments"
        },
        {
          "id": "http://vocab.getty.edu/aat/300418049",
          "type": "Type",
          "_label": "brief texts"
        }
      ]
    }
  ],
  "produced_by": [
    {
      "id": "https://clevelandart.org/art/object/1924.655/production",
      "type": "Production",
      "_label": "Production of the Object"
    },
    {
      "carried_out_by": [
        {
          "id": "https://clevelandart.org/art/actor/1924.655",
          "type": "Actor",
          "_label": ""
        }
      ]
    },
    {
      "timespan": {
        "id": "https://clevelandart.org/art/1924.655/production/timespan",
        "type": "TimeSpan",
        "_label": "c. 1648-54",
        "begin_of_the_begin": "1643",
        "end_of_the_end": "1659"
      }
    }
  ]
}