{
  "@context": "https://linked.art/ns/v1/linked-art.json",
  "id": "https://clevelandart.org/art/1929.85",
  "type": "HumanMadeObject",
  "_label": "Silk Fragment",
  "identified_by": [
    {
      "id": "https://clevelandart.org/art/object/1929.85/title",
      "type": "Name",
      "_label": "Primary Title for the Object",
      "content": "Silk Fragment",
      "classified_as": [
        {
          "id": "http://vocab.getty.edu/aat/300404670",
          "type": "Type",
          "_label": "preferred terms"
        }
      ]
    }
  ],
  "referred_to_by": [
    {
      "id": "https://clevelandart.org/art/object/1929.85/provenance-statement",
      "type": "LinguisticObject",
      "_label": "Provenance Statement about the Object",
      "content": "found in a 12th century reliquary in church near Barcelona, Spain.  (Adolph Loewi, Venice).",
      "classified_as": [
        {
          "id": "http://vocab.getty.edu/aat/300055863",
          "type": "Type",
          "_label": "provenance (history of ownership)"
        },
        {
          "id": "http://vocab.getty.edu/aat/300418049",
          "type": "Type",
          "_label": "brief texts"
        }
      ]
    }
  ],
  "produced_by": [
    {
      "id": "https://clevelandart.org/art/object/1929.85/production",
      "type": "Production",
      "_label": "Production of the Object"
    },
    {
      "carried_out_by": [
        {
          "id": "https://clevelandart.org/art/actor/1929.85",
          "type": "Actor",
          "_label": ""
        }
      ]
    },
    {
      "timespan": {
        "id": "https://clevelandart.org/art/1929.85/production/timespan",
        "type": "TimeSpan",
        "_label": "second half of 12th century",
        "begin_of_the_begin": "1150",
        "end_of_the_end": "1199"
      }
    }
  ]
}