{
  "@context": "https://linked.art/ns/v1/linked-art.json",
  "id": "https://clevelandart.org/art/1957.368.b",
  "type": "HumanMadeObject",
  "_label": "Lid for a Tea Kettle",
  "identified_by": [
    {
      "id": "https://clevelandart.org/art/object/1957.368.b/title",
      "type": "Name",
      "_label": "Primary Title for the Object",
      "content": "Lid for a Tea Kettle",
      "classified_as": [
        {
          "id": "http://vocab.getty.edu/aat/300404670",
          "type": "Type",
          "_label": "preferred terms"
        }
      ]
    }
  ],
  "referred_to_by": [],
  "produced_by": [
    {
      "id": "https://clevelandart.org/art/object/1957.368.b/production",
      "type": "Production",
      "_label": "Production of the Object"
    },
    {
      "carried_out_by": [
        {
          "id": "https://clevelandart.org/art/actor/1957.368.b",
          "type": "Actor",
          "_label": ""
        }
      ]
    },
    {
      "timespan": {
        "id": "https://clevelandart.org/art/1957.368.b/production/timespan",
        "type": "TimeSpan",
        "_label": "c 1950s",
        "begin_of_the_begin": "1950",
        "end_of_the_end": "1957"
      }
    }
  ]
}