{
  "@context": "https://linked.art/ns/v1/linked-art.json",
  "id": "https://clevelandart.org/art/1969.50",
  "type": "HumanMadeObject",
  "_label": "Corpus of Christ",
  "identified_by": [
    {
      "id": "https://clevelandart.org/art/object/1969.50/title",
      "type": "Name",
      "_label": "Primary Title for the Object",
      "content": "Corpus of Christ",
      "classified_as": [
        {
          "id": "http://vocab.getty.edu/aat/300404670",
          "type": "Type",
          "_label": "preferred terms"
        }
      ]
    }
  ],
  "referred_to_by": [
    {
      "id": "https://clevelandart.org/art/object/1969.50/provenance-statement",
      "type": "LinguisticObject",
      "_label": "Provenance Statement about the Object",
      "content": "(J. J. Klejman, New York).",
      "classified_as": [
        {
          "id": "http://vocab.getty.edu/aat/300055863",
          "type": "Type",
          "_label": "provenance (history of ownership)"
        },
        {
          "id": "http://vocab.getty.edu/aat/300418049",
          "type": "Type",
          "_label": "brief texts"
        }
      ]
    }
  ],
  "produced_by": [
    {
      "id": "https://clevelandart.org/art/object/1969.50/production",
      "type": "Production",
      "_label": "Production of the Object"
    },
    {
      "carried_out_by": [
        {
          "id": "https://clevelandart.org/art/actor/1969.50",
          "type": "Actor",
          "_label": ""
        }
      ]
    },
    {
      "timespan": {
        "id": "https://clevelandart.org/art/1969.50/production/timespan",
        "type": "TimeSpan",
        "_label": "c. 1150-1175",
        "begin_of_the_begin": "1150",
        "end_of_the_end": "1175"
      }
    }
  ]
}