{
  "@context": "https://linked.art/ns/v1/linked-art.json",
  "id": "https://clevelandart.org/art/1969.86.6",
  "type": "HumanMadeObject",
  "_label": "Through My Berkeley Windows:  Sour Cherry",
  "identified_by": [
    {
      "id": "https://clevelandart.org/art/object/1969.86.6/title",
      "type": "Name",
      "_label": "Primary Title for the Object",
      "content": "Through My Berkeley Windows:  Sour Cherry",
      "classified_as": [
        {
          "id": "http://vocab.getty.edu/aat/300404670",
          "type": "Type",
          "_label": "preferred terms"
        }
      ]
    }
  ],
  "referred_to_by": [
    {
      "id": "https://clevelandart.org/art/object/1969.86.6/credit-line",
      "type": "LinguisticObject",
      "_label": "Credit Line for the Object",
      "content": "Betty Lark-Horovitz (American, 1894-1995), artist",
      "classified_as": [
        {
          "id": "http://vocab.getty.edu/aat/300026687",
          "type": "Type",
          "_label": "acknowledgments"
        },
        {
          "id": "http://vocab.getty.edu/aat/300418049",
          "type": "Type",
          "_label": "brief texts"
        }
      ]
    }
  ],
  "produced_by": [
    {
      "id": "https://clevelandart.org/art/object/1969.86.6/production",
      "type": "Production",
      "_label": "Production of the Object"
    },
    {
      "carried_out_by": [
        {
          "id": "https://clevelandart.org/art/actor/1969.86.6",
          "type": "Actor",
          "_label": ""
        }
      ]
    }
  ]
}