{
  "@context": "https://linked.art/ns/v1/linked-art.json",
  "id": "https://clevelandart.org/art/1975.105",
  "type": "HumanMadeObject",
  "_label": "Tabernacle Relief with Flanking Angels",
  "identified_by": [
    {
      "id": "https://clevelandart.org/art/object/1975.105/title",
      "type": "Name",
      "_label": "Primary Title for the Object",
      "content": "Tabernacle Relief with Flanking Angels",
      "classified_as": [
        {
          "id": "http://vocab.getty.edu/aat/300404670",
          "type": "Type",
          "_label": "preferred terms"
        }
      ]
    }
  ],
  "referred_to_by": [
    {
      "id": "https://clevelandart.org/art/object/1975.105/credit-line",
      "type": "LinguisticObject",
      "_label": "Credit Line for the Object",
      "content": "Tullio Lombardo (Italian, c. 1455-1532), artist",
      "classified_as": [
        {
          "id": "http://vocab.getty.edu/aat/300026687",
          "type": "Type",
          "_label": "acknowledgments"
        },
        {
          "id": "http://vocab.getty.edu/aat/300418049",
          "type": "Type",
          "_label": "brief texts"
        }
      ]
    },
    {
      "id": "https://clevelandart.org/art/object/1975.105/provenance-statement",
      "type": "LinguisticObject",
      "_label": "Provenance Statement about the Object",
      "content": "Heinrich Miller con Aicholz (Vienna, Austria), by forced sale to the City of Vienna, 1938; 1938-1945  City of Vienna, occupied after World War II by the French government; 1945 -   French government; Camillo Castiglioni, 1959-1957 (Vienna, Austria); Jacques Seligmann and Co., sold to the Cleveland Museum of Art, 1975.",
      "classified_as": [
        {
          "id": "http://vocab.getty.edu/aat/300055863",
          "type": "Type",
          "_label": "provenance (history of ownership)"
        },
        {
          "id": "http://vocab.getty.edu/aat/300418049",
          "type": "Type",
          "_label": "brief texts"
        }
      ]
    }
  ],
  "produced_by": [
    {
      "id": "https://clevelandart.org/art/object/1975.105/production",
      "type": "Production",
      "_label": "Production of the Object"
    },
    {
      "carried_out_by": [
        {
          "id": "https://clevelandart.org/art/actor/1975.105",
          "type": "Actor",
          "_label": ""
        }
      ]
    },
    {
      "timespan": {
        "id": "https://clevelandart.org/art/1975.105/production/timespan",
        "type": "TimeSpan",
        "_label": "c. 1480-1500",
        "begin_of_the_begin": "1475",
        "end_of_the_end": "1505"
      }
    }
  ]
}