{
  "@context": "https://linked.art/ns/v1/linked-art.json",
  "id": "https://clevelandart.org/art/2008.146",
  "type": "HumanMadeObject",
  "_label": "Brocaded velvet cover with sunbursts",
  "identified_by": [
    {
      "id": "https://clevelandart.org/art/object/2008.146/title",
      "type": "Name",
      "_label": "Primary Title for the Object",
      "content": "Brocaded velvet cover with sunbursts",
      "classified_as": [
        {
          "id": "http://vocab.getty.edu/aat/300404670",
          "type": "Type",
          "_label": "preferred terms"
        }
      ]
    }
  ],
  "referred_to_by": [],
  "produced_by": [
    {
      "id": "https://clevelandart.org/art/object/2008.146/production",
      "type": "Production",
      "_label": "Production of the Object"
    },
    {
      "carried_out_by": [
        {
          "id": "https://clevelandart.org/art/actor/2008.146",
          "type": "Actor",
          "_label": ""
        }
      ]
    },
    {
      "timespan": {
        "id": "https://clevelandart.org/art/2008.146/production/timespan",
        "type": "TimeSpan",
        "_label": "early 1600s",
        "begin_of_the_begin": "1600",
        "end_of_the_end": "1630"
      }
    }
  ]
}