{
  "@context": "https://linked.art/ns/v1/linked-art.json",
  "id": "https://clevelandart.org/art/2011.72",
  "type": "HumanMadeObject",
  "_label": "Sleeping Gypsy ",
  "identified_by": [
    {
      "id": "https://clevelandart.org/art/object/2011.72/title",
      "type": "Name",
      "_label": "Primary Title for the Object",
      "content": "Sleeping Gypsy ",
      "classified_as": [
        {
          "id": "http://vocab.getty.edu/aat/300404670",
          "type": "Type",
          "_label": "preferred terms"
        }
      ]
    }
  ],
  "referred_to_by": [
    {
      "id": "https://clevelandart.org/art/object/2011.72/credit-line",
      "type": "LinguisticObject",
      "_label": "Credit Line for the Object",
      "content": "Robert Rafailovich Falk (Russian, 1886-1958), artist",
      "classified_as": [
        {
          "id": "http://vocab.getty.edu/aat/300026687",
          "type": "Type",
          "_label": "acknowledgments"
        },
        {
          "id": "http://vocab.getty.edu/aat/300418049",
          "type": "Type",
          "_label": "brief texts"
        }
      ]
    },
    {
      "id": "https://clevelandart.org/art/object/2011.72/provenance-statement",
      "type": "LinguisticObject",
      "_label": "Provenance Statement about the Object",
      "content": "(Leonard Hutton Galleries, New York, NY, 1968, sold to Dr. Paul J. Vignos, Jr.) (1968); Dr. Paul J. Vignos, Jr. [1919-2010] Gates Mills, OH, by bequest to the Cleveland Museum of Art (1968-2011); The Cleveland Museum of Art, Cleveland, OH (2011-)",
      "classified_as": [
        {
          "id": "http://vocab.getty.edu/aat/300055863",
          "type": "Type",
          "_label": "provenance (history of ownership)"
        },
        {
          "id": "http://vocab.getty.edu/aat/300418049",
          "type": "Type",
          "_label": "brief texts"
        }
      ]
    }
  ],
  "produced_by": [
    {
      "id": "https://clevelandart.org/art/object/2011.72/production",
      "type": "Production",
      "_label": "Production of the Object"
    },
    {
      "carried_out_by": [
        {
          "id": "https://clevelandart.org/art/actor/2011.72",
          "type": "Actor",
          "_label": ""
        }
      ]
    },
    {
      "timespan": {
        "id": "https://clevelandart.org/art/2011.72/production/timespan",
        "type": "TimeSpan",
        "_label": "c. 1909-1912",
        "begin_of_the_begin": "1904",
        "end_of_the_end": "1917"
      }
    }
  ]
}