{
  "@context": "https://linked.art/ns/v1/linked-art.json",
  "id": "https://clevelandart.org/art/2015.132",
  "type": "HumanMadeObject",
  "_label": "Bivouac de Cosaques",
  "identified_by": [
    {
      "id": "https://clevelandart.org/art/object/2015.132/title",
      "type": "Name",
      "_label": "Primary Title for the Object",
      "content": "Bivouac de Cosaques",
      "classified_as": [
        {
          "id": "http://vocab.getty.edu/aat/300404670",
          "type": "Type",
          "_label": "preferred terms"
        }
      ]
    }
  ],
  "referred_to_by": [
    {
      "id": "https://clevelandart.org/art/object/2015.132/credit-line",
      "type": "LinguisticObject",
      "_label": "Credit Line for the Object",
      "content": "Carle Vernet (French, 1758-1836), artist; C.F.X. Gastel, Bould. St. Martin No. 6, published by",
      "classified_as": [
        {
          "id": "http://vocab.getty.edu/aat/300026687",
          "type": "Type",
          "_label": "acknowledgments"
        },
        {
          "id": "http://vocab.getty.edu/aat/300418049",
          "type": "Type",
          "_label": "brief texts"
        }
      ]
    }
  ],
  "produced_by": [
    {
      "id": "https://clevelandart.org/art/object/2015.132/production",
      "type": "Production",
      "_label": "Production of the Object"
    },
    {
      "carried_out_by": [
        {
          "id": "https://clevelandart.org/art/actor/2015.132",
          "type": "Actor",
          "_label": ""
        }
      ]
    }
  ]
}