{
  "@context": "https://linked.art/ns/v1/linked-art.json",
  "id": "https://clevelandart.org/art/1915.25",
  "type": "HumanMadeObject",
  "_label": "Bead in the Form of a Shell",
  "identified_by": [
    {
      "id": "https://clevelandart.org/art/object/1915.25/title",
      "type": "Name",
      "_label": "Primary Title for the Object",
      "content": "Bead in the Form of a Shell",
      "classified_as": [
        {
          "id": "http://vocab.getty.edu/aat/300404670",
          "type": "Type",
          "_label": "preferred terms"
        }
      ]
    }
  ],
  "referred_to_by": [],
  "produced_by": [
    {
      "id": "https://clevelandart.org/art/object/1915.25/production",
      "type": "Production",
      "_label": "Production of the Object"
    },
    {
      "carried_out_by": [
        {
          "id": "https://clevelandart.org/art/actor/1915.25",
          "type": "Actor",
          "_label": ""
        }
      ]
    },
    {
      "timespan": {
        "id": "https://clevelandart.org/art/1915.25/production/timespan",
        "type": "TimeSpan",
        "_label": "2040-1648 BC",
        "begin_of_the_begin": "-2040",
        "end_of_the_end": "-1648"
      }
    }
  ]
}