{
  "@context": "https://linked.art/ns/v1/linked-art.json",
  "id": "https://www.nga.gov/collection/1939.1.261.a",
  "type": "HumanMadeObject",
  "_label": "Saint Peter [left panel]",
  "identified_by": [
    {
      "id": "https://www.nga.gov/collection/object/1939.1.261.a/title",
      "type": "Name",
      "_label": "Primary Title for the Object",
      "content": "Saint Peter [left panel]",
      "classified_as": [
        {
          "id": "http://vocab.getty.edu/aat/300404670",
          "type": "Type",
          "_label": "preferred terms"
        }
      ]
    }
  ],
  "referred_to_by": [
    {
      "id": "https://www.nga.gov/collection/object/1939.1.261.a/credit-line",
      "type": "LinguisticObject",
      "_label": "Credit Line for the Object",
      "content": "Samuel H. Kress Collection",
      "classified_as": [
        {
          "id": "http://vocab.getty.edu/aat/300026687",
          "type": "Type",
          "_label": "acknowledgments"
        },
        {
          "id": "http://vocab.getty.edu/aat/300418049",
          "type": "Type",
          "_label": "brief texts"
        }
      ]
    }
  ],
  "produced_by": [
    {
      "id": "https://www.nga.gov/collection/object/1939.1.261.a/production",
      "type": "Production",
      "_label": "Production of the Object"
    },
    {
      "carried_out_by": [
        {
          "id": "https://www.nga.gov/collection/actor/1939.1.261.a",
          "type": "Actor",
          "_label": "Nardo di Cione"
        }
      ]
    },
    {
      "timespan": {
        "id": "https://www.nga.gov/collection/1939.1.261.a/production/timespan",
        "type": "TimeSpan",
        "_label": "c. 1360",
        "begin_of_the_begin": "1360",
        "end_of_the_end": "1360"
      }
    }
  ]
}